{
  "code": 200,
  "status": "success",
  "data": [
    {
      "type": "Node",
      "name": "gke-prod-node-01",
      "resourceId": "node/gke-01",
      "totalCost": 48.75,
      "cpuCost": 32.40,
      "ramCost": 16.35,
      "status": "Running",
      "category": "Compute",
      "provider": "GCP",
      "cluster": "gke-prod-us"
    },
    {
      "type": "Node",
      "name": "gke-prod-node-02",
      "resourceId": "node/gke-02",
      "totalCost": 52.10,
      "cpuCost": 35.00,
      "ramCost": 17.10,
      "status": "Running",
      "category": "Compute",
      "provider": "GCP",
      "cluster": "gke-prod-us"
    },
    {
      "type": "Node",
      "name": "gke-prod-node-03",
      "resourceId": "node/gke-03",
      "totalCost": 49.50,
      "cpuCost": 33.00,
      "ramCost": 16.50,
      "status": "Running",
      "category": "Compute",
      "provider": "GCP",
      "cluster": "gke-prod-us"
    },
    {
      "type": "Pod",
      "name": "frontend-app-replica-1",
      "resourceId": "pod/fe-01",
      "totalCost": 12.50,
      "cpuCost": 8.00,
      "ramCost": 4.50,
      "status": "Running",
      "category": "Workload",
      "provider": "GCP",
      "cluster": "gke-prod-us"
    },
    {
      "type": "Pod",
      "name": "frontend-app-replica-2",
      "resourceId": "pod/fe-02",
      "totalCost": 12.50,
      "cpuCost": 8.00,
      "ramCost": 4.50,
      "status": "Running",
      "category": "Workload",
      "provider": "GCP",
      "cluster": "gke-prod-us"
    },
    {
      "type": "Service",
      "name": "frontend-lb",
      "resourceId": "svc/fe-lb",
      "totalCost": 25.00,
      "cpuCost": 15.00,
      "ramCost": 10.00,
      "status": "Active",
      "category": "Network",
      "provider": "GCP",
      "cluster": "gke-prod-us"
    },
    {
      "type": "Node",
      "name": "aks-fin-node-01",
      "resourceId": "node/aks-01",
      "totalCost": 65.00,
      "cpuCost": 45.00,
      "ramCost": 20.00,
      "status": "Running",
      "category": "Compute",
      "provider": "Azure",
      "cluster": "aks-finance-eu"
    },
    {
      "type": "Node",
      "name": "aks-fin-node-02",
      "resourceId": "node/aks-02",
      "totalCost": 64.50,
      "cpuCost": 44.50,
      "ramCost": 20.00,
      "status": "Running",
      "category": "Compute",
      "provider": "Azure",
      "cluster": "aks-finance-eu"
    },
    {
      "type": "Pod",
      "name": "payment-processor-01",
      "resourceId": "pod/pay-01",
      "totalCost": 22.00,
      "cpuCost": 15.00,
      "ramCost": 7.00,
      "status": "Running",
      "category": "Workload",
      "provider": "Azure",
      "cluster": "aks-finance-eu"
    },
    {
      "type": "Pod",
      "name": "payment-processor-02",
      "resourceId": "pod/pay-02",
      "totalCost": 22.00,
      "cpuCost": 15.00,
      "ramCost": 7.00,
      "status": "Running",
      "category": "Workload",
      "provider": "Azure",
      "cluster": "aks-finance-eu"
    },
    {
      "type": "Storage",
      "name": "ledger-db-disk",
      "resourceId": "disk/led-01",
      "totalCost": 45.00,
      "cpuCost": 0,
      "ramCost": 0,
      "status": "Mounted",
      "category": "Storage",
      "provider": "Azure",
      "cluster": "aks-finance-eu"
    },
    {
      "type": "Namespace",
      "name": "finance-prod",
      "resourceId": "ns/fin-prod",
      "totalCost": 180.00,
      "cpuCost": 100.00,
      "ramCost": 80.00,
      "status": "Active",
      "category": "Orchestration",
      "provider": "Azure",
      "cluster": "aks-finance-eu"
    },
    {
      "type": "Node",
      "name": "eks-ml-gpu-01",
      "resourceId": "node/eks-gpu-01",
      "totalCost": 120.00,
      "cpuCost": 50.00,
      "ramCost": 70.00,
      "status": "Running",
      "category": "Compute",
      "provider": "AWS",
      "cluster": "eks-ml-research"
    },
    {
      "type": "Node",
      "name": "eks-ml-gpu-02",
      "resourceId": "node/eks-gpu-02",
      "totalCost": 125.00,
      "cpuCost": 52.00,
      "ramCost": 73.00,
      "status": "Running",
      "category": "Compute",
      "provider": "AWS",
      "cluster": "eks-ml-research"
    },
    {
      "type": "Pod",
      "name": "training-job-v4",
      "resourceId": "pod/train-04",
      "totalCost": 85.00,
      "cpuCost": 40.00,
      "ramCost": 45.00,
      "status": "Running",
      "category": "Workload",
      "provider": "AWS",
      "cluster": "eks-ml-research"
    },
    {
      "type": "Storage",
      "name": "dataset-volume-large",
      "resourceId": "disk/data-lg",
      "totalCost": 250.00,
      "cpuCost": 0,
      "ramCost": 0,
      "status": "Mounted",
      "category": "Storage",
      "provider": "AWS",
      "cluster": "eks-ml-research"
    },
    {
      "type": "Node",
      "name": "ocp-metal-01",
      "resourceId": "node/ocp-01",
      "totalCost": 15.00,
      "cpuCost": 10.00,
      "ramCost": 5.00,
      "status": "Running",
      "category": "Compute",
      "provider": "On-Prem",
      "cluster": "ocp-datacenter-ny"
    },
    {
      "type": "Node",
      "name": "ocp-metal-02",
      "resourceId": "node/ocp-02",
      "totalCost": 15.00,
      "cpuCost": 10.00,
      "ramCost": 5.00,
      "status": "Running",
      "category": "Compute",
      "provider": "On-Prem",
      "cluster": "ocp-datacenter-ny"
    },
    {
      "type": "Node",
      "name": "ocp-metal-03",
      "resourceId": "node/ocp-03",
      "totalCost": 15.00,
      "cpuCost": 10.00,
      "ramCost": 5.00,
      "status": "Running",
      "category": "Compute",
      "provider": "On-Prem",
      "cluster": "ocp-datacenter-ny"
    },
    {
      "type": "Service",
      "name": "internal-router",
      "resourceId": "svc/int-rtr",
      "totalCost": 5.00,
      "cpuCost": 3.00,
      "ramCost": 2.00,
      "status": "Active",
      "category": "Network",
      "provider": "On-Prem",
      "cluster": "ocp-datacenter-ny"
    },
    {
      "type": "Pod",
      "name": "legacy-app-01",
      "resourceId": "pod/leg-01",
      "totalCost": 8.50,
      "cpuCost": 5.00,
      "ramCost": 3.50,
      "status": "Running",
      "category": "Workload",
      "provider": "On-Prem",
      "cluster": "ocp-datacenter-ny"
    },
    {
      "type": "Node",
      "name": "aks-dev-01",
      "resourceId": "node/aks-dev-01",
      "totalCost": 30.00,
      "cpuCost": 20.00,
      "ramCost": 10.00,
      "status": "Running",
      "category": "Compute",
      "provider": "Azure",
      "cluster": "aks-dev-cluster"
    },
    {
      "type": "Pod",
      "name": "dev-env-user-1",
      "resourceId": "pod/dev-u1",
      "totalCost": 5.00,
      "cpuCost": 3.00,
      "ramCost": 2.00,
      "status": "Running",
      "category": "Workload",
      "provider": "Azure",
      "cluster": "aks-dev-cluster"
    },
    {
      "type": "Pod",
      "name": "dev-env-user-2",
      "resourceId": "pod/dev-u2",
      "totalCost": 5.00,
      "cpuCost": 3.00,
      "ramCost": 2.00,
      "status": "Running",
      "category": "Workload",
      "provider": "Azure",
      "cluster": "aks-dev-cluster"
    },
    {
      "type": "Pod",
      "name": "ci-runner-01",
      "resourceId": "pod/ci-01",
      "totalCost": 12.00,
      "cpuCost": 8.00,
      "ramCost": 4.00,
      "status": "Running",
      "category": "Workload",
      "provider": "Azure",
      "cluster": "aks-dev-cluster"
    },
    {
      "type": "Node",
      "name": "eks-spot-01",
      "resourceId": "node/eks-spot-01",
      "totalCost": 12.50,
      "cpuCost": 8.00,
      "ramCost": 4.50,
      "status": "Running",
      "category": "Compute",
      "provider": "AWS",
      "cluster": "eks-batch-jobs"
    },
    {
      "type": "Node",
      "name": "eks-spot-02",
      "resourceId": "node/eks-spot-02",
      "totalCost": 11.80,
      "cpuCost": 7.50,
      "ramCost": 4.30,
      "status": "Running",
      "category": "Compute",
      "provider": "AWS",
      "cluster": "eks-batch-jobs"
    },
    {
      "type": "Job",
      "name": "nightly-report",
      "resourceId": "job/nightly",
      "totalCost": 4.50,
      "cpuCost": 3.00,
      "ramCost": 1.50,
      "status": "Completed",
      "category": "Workload",
      "provider": "AWS",
      "cluster": "eks-batch-jobs"
    },
    {
      "type": "Job",
      "name": "data-cleanup",
      "resourceId": "job/cleanup",
      "totalCost": 3.20,
      "cpuCost": 2.00,
      "ramCost": 1.20,
      "status": "Completed",
      "category": "Workload",
      "provider": "AWS",
      "cluster": "eks-batch-jobs"
    },
    {
      "type": "Storage",
      "name": "unused-disk-01",
      "resourceId": "disk/unused-01",
      "totalCost": 10.00,
      "cpuCost": 0,
      "ramCost": 0,
      "status": "Detached",
      "category": "Storage",
      "provider": "GCP",
      "cluster": "gke-prod-us"
    },
    {
      "type": "Storage",
      "name": "unused-disk-02",
      "resourceId": "disk/unused-02",
      "totalCost": 15.00,
      "cpuCost": 0,
      "ramCost": 0,
      "status": "Detached",
      "category": "Storage",
      "provider": "AWS",
      "cluster": "eks-ml-research"
    },
    {
      "type": "LoadBalancer",
      "name": "api-gateway-ext",
      "resourceId": "lb/api-gw",
      "totalCost": 35.00,
      "cpuCost": 20.00,
      "ramCost": 15.00,
      "status": "Active",
      "category": "Network",
      "provider": "AWS",
      "cluster": "eks-prod-api"
    },
    {
      "type": "Node",
      "name": "eks-api-node-01",
      "resourceId": "node/api-01",
      "totalCost": 40.00,
      "cpuCost": 25.00,
      "ramCost": 15.00,
      "status": "Running",
      "category": "Compute",
      "provider": "AWS",
      "cluster": "eks-prod-api"
    },
    {
      "type": "Node",
      "name": "eks-api-node-02",
      "resourceId": "node/api-02",
      "totalCost": 40.00,
      "cpuCost": 25.00,
      "ramCost": 15.00,
      "status": "Running",
      "category": "Compute",
      "provider": "AWS",
      "cluster": "eks-prod-api"
    },
    {
      "type": "Node",
      "name": "gke-staging-01",
      "resourceId": "node/stg-01",
      "totalCost": 25.00,
      "cpuCost": 15.00,
      "ramCost": 10.00,
      "status": "Running",
      "category": "Compute",
      "provider": "GCP",
      "cluster": "gke-staging"
    },
    {
      "type": "Pod",
      "name": "staging-app-01",
      "resourceId": "pod/stg-app",
      "totalCost": 8.00,
      "cpuCost": 5.00,
      "ramCost": 3.00,
      "status": "Running",
      "category": "Workload",
      "provider": "GCP",
      "cluster": "gke-staging"
    },
    {
      "type": "Namespace",
      "name": "monitoring",
      "resourceId": "ns/mon",
      "totalCost": 60.00,
      "cpuCost": 40.00,
      "ramCost": 20.00,
      "status": "Active",
      "category": "Orchestration",
      "provider": "On-Prem",
      "cluster": "ocp-datacenter-ny"
    },
    {
      "type": "Pod",
      "name": "prometheus-0",
      "resourceId": "pod/prom-0",
      "totalCost": 15.00,
      "cpuCost": 10.00,
      "ramCost": 5.00,
      "status": "Running",
      "category": "Workload",
      "provider": "On-Prem",
      "cluster": "ocp-datacenter-ny"
    },
    {
      "type": "Pod",
      "name": "grafana-0",
      "resourceId": "pod/graf-0",
      "totalCost": 5.00,
      "cpuCost": 2.00,
      "ramCost": 3.00,
      "status": "Running",
      "category": "Workload",
      "provider": "On-Prem",
      "cluster": "ocp-datacenter-ny"
    },
    {
      "type": "LoadBalancer",
      "name": "internal-api-lb",
      "resourceId": "lb/int-api",
      "totalCost": 22.00,
      "cpuCost": 12.00,
      "ramCost": 10.00,
      "status": "Active",
      "category": "Network",
      "provider": "Azure",
      "cluster": "aks-dev-cluster"
    },
    {
      "type": "Node",
      "name": "aks-backup-01",
      "resourceId": "node/bkp-01",
      "totalCost": 28.00,
      "cpuCost": 18.00,
      "ramCost": 10.00,
      "status": "Running",
      "category": "Compute",
      "provider": "Azure",
      "cluster": "aks-backup-dr"
    },
    {
      "type": "Storage",
      "name": "backup-volume-01",
      "resourceId": "disk/bkp-vol",
      "totalCost": 80.00,
      "cpuCost": 0,
      "ramCost": 0,
      "status": "Mounted",
      "category": "Storage",
      "provider": "Azure",
      "cluster": "aks-backup-dr"
    },
    {
      "type": "Pod",
      "name": "redis-cache-0",
      "resourceId": "pod/redis-0",
      "totalCost": 18.00,
      "cpuCost": 10.00,
      "ramCost": 8.00,
      "status": "Running",
      "category": "Workload",
      "provider": "GCP",
      "cluster": "gke-prod-us"
    },
    {
      "type": "Pod",
      "name": "redis-cache-1",
      "resourceId": "pod/redis-1",
      "totalCost": 18.00,
      "cpuCost": 10.00,
      "ramCost": 8.00,
      "status": "Running",
      "category": "Workload",
      "provider": "GCP",
      "cluster": "gke-prod-us"
    },
    {
      "type": "Pod",
      "name": "redis-cache-2",
      "resourceId": "pod/redis-2",
      "totalCost": 18.00,
      "cpuCost": 10.00,
      "ramCost": 8.00,
      "status": "Running",
      "category": "Workload",
      "provider": "GCP",
      "cluster": "gke-prod-us"
    },
    {
      "type": "Service",
      "name": "redis-svc",
      "resourceId": "svc/redis",
      "totalCost": 8.00,
      "cpuCost": 5.00,
      "ramCost": 3.00,
      "status": "Active",
      "category": "Network",
      "provider": "GCP",
      "cluster": "gke-prod-us"
    },
    {
      "type": "Namespace",
      "name": "kube-system",
      "resourceId": "ns/kube-sys",
      "totalCost": 45.00,
      "cpuCost": 25.00,
      "ramCost": 20.00,
      "status": "Active",
      "category": "Orchestration",
      "provider": "On-Prem",
      "cluster": "ocp-datacenter-ny"
    }
  ]
}